{
  "mqtt": {
    "options": {
      "clientId": "some-id",
      "username": "name",
      "password": "password"
    },
    "url": "tls://example.com:8883"
  },
  "logTopic": "home/note/logs",
  "tasksConfig": {
    "CheckProcess": {
      "topic": "home/note/steam",
      "process": "steam"
    },
    "GetNetwork": {
      "topic": "home/note/net"
    },
    "GetCpuUsage": {
      "topic": "home/note/cpu"
    },
    "SetOnline": {
      "topic": "home/note/online"
    },
    "TimeControl": {
      "topicDelay": "home/note/delay",
      "topicForceOff": "home/note/forceoff",
      "topicShutdown": "home/note/shutdown",
      "allowedTime": [{"start": 7, "end": 22}]
    }
  }
}
